cim_sdk/__init__.py
cim_sdk/client.py
cim_sdk/config.py
cim_sdk/http.py
cim_sdk/orders.py
cim_sdk/products.py
cim_sdk/subapi.py
cim_sdk/token_manager.py
cim_sdk/transactions.py
cim_sdk-0.1.4.dist-info/METADATA
cim_sdk-0.1.4.dist-info/WHEEL
cim_sdk-0.1.4.dist-info/top_level.txt
cim_sdk-0.1.4.dist-info/RECORD
