Metadata-Version: 2.4
Name: cim-sdk
Version: 0.1.4
Summary: Unofficial Python SDK for the CameronSino CIM Admin API.
Author: Json
License: MIT
Requires-Python: >=3.8
Requires-Dist: requests>=2.31.0
